{
  "Name":           "libsodium",
  "SourceUrl":      "https://github.com/jedisct1/libsodium/tags",
  "Maintainer":     "Andrey P.",
  "MaintainerUrl":  "http://abi-laboratory.pro/",
  "HeadersDiff":    "Off",

  "Versions": [
  {
    "Number":         "1.0.16",
    "Installed":      "installed/libsodium/1.0.16",
    "Source":         "src/libsodium/1.0.16/libsodium-1.0.16.tar.gz",
    "Changelog":      "ChangeLog",
    "HeadersDiff":    "Off",
    "PkgDiff":        "Off",
    "ABIView":        "Off",
    "ABIDiff":        "Off"
  },
  {
    "Number":         "1.0.15",
    "Installed":      "installed/libsodium/1.0.15",
    "Source":         "src/libsodium/1.0.15/libsodium-1.0.15.tar.gz",
    "Changelog":      "ChangeLog",
    "HeadersDiff":    "Off",
    "PkgDiff":        "Off",
    "ABIView":        "Off",
    "ABIDiff":        "Off"
  },
  {
    "Number":         "1.0.14",
    "Installed":      "installed/libsodium/1.0.14",
    "Source":         "src/libsodium/1.0.14/libsodium-1.0.14.tar.gz",
    "Changelog":      "ChangeLog",
    "HeadersDiff":    "Off",
    "PkgDiff":        "Off",
    "ABIView":        "Off",
    "ABIDiff":        "Off"
  },
  {
    "Number":         "1.0.13",
    "Installed":      "installed/libsodium/1.0.13",
    "Source":         "src/libsodium/1.0.13/libsodium-1.0.13.tar.gz",
    "Changelog":      "ChangeLog",
    "HeadersDiff":    "Off",
    "PkgDiff":        "Off",
    "ABIView":        "Off",
    "ABIDiff":        "Off"
  },
  {
    "Number":         "1.0.12",
    "Installed":      "installed/libsodium/1.0.12",
    "Source":         "src/libsodium/1.0.12/libsodium-1.0.12.tar.gz",
    "Changelog":      "ChangeLog",
    "HeadersDiff":    "Off",
    "PkgDiff":        "Off",
    "ABIView":        "Off",
    "ABIDiff":        "Off"
  },
  {
    "Number":         "1.0.11",
    "Installed":      "installed/libsodium/1.0.11",
    "Source":         "src/libsodium/1.0.11/libsodium-1.0.11.tar.gz",
    "Changelog":      "ChangeLog",
    "HeadersDiff":    "Off",
    "PkgDiff":        "Off",
    "ABIView":        "Off",
    "ABIDiff":        "Off"
  },
  {
    "Number":         "1.0.10",
    "Installed":      "installed/libsodium/1.0.10",
    "Source":         "src/libsodium/1.0.10/libsodium-1.0.10.tar.gz",
    "Changelog":      "ChangeLog",
    "HeadersDiff":    "Off",
    "PkgDiff":        "Off",
    "ABIView":        "Off",
    "ABIDiff":        "Off"
  },
  {
    "Number":         "1.0.9",
    "Installed":      "installed/libsodium/1.0.9",
    "Source":         "src/libsodium/1.0.9/libsodium-1.0.9.tar.gz",
    "Changelog":      "ChangeLog",
    "HeadersDiff":    "Off",
    "PkgDiff":        "Off",
    "ABIView":        "Off",
    "ABIDiff":        "Off"
  },
  {
    "Number":         "1.0.8",
    "Installed":      "installed/libsodium/1.0.8",
    "Source":         "src/libsodium/1.0.8/libsodium-1.0.8.tar.gz",
    "Changelog":      "ChangeLog",
    "HeadersDiff":    "Off",
    "PkgDiff":        "Off",
    "ABIView":        "Off",
    "ABIDiff":        "Off"
  },
  {
    "Number":         "1.0.7",
    "Installed":      "installed/libsodium/1.0.7",
    "Source":         "src/libsodium/1.0.7/libsodium-1.0.7.tar.gz",
    "Changelog":      "ChangeLog",
    "HeadersDiff":    "Off",
    "PkgDiff":        "Off",
    "ABIView":        "Off",
    "ABIDiff":        "Off"
  },
  {
    "Number":         "1.0.6",
    "Installed":      "installed/libsodium/1.0.6",
    "Source":         "src/libsodium/1.0.6/libsodium-1.0.6.tar.gz",
    "Changelog":      "ChangeLog",
    "HeadersDiff":    "Off",
    "PkgDiff":        "Off",
    "ABIView":        "Off",
    "ABIDiff":        "Off"
  },
  {
    "Number":         "1.0.5",
    "Installed":      "installed/libsodium/1.0.5",
    "Source":         "src/libsodium/1.0.5/libsodium-1.0.5.tar.gz",
    "Changelog":      "ChangeLog",
    "HeadersDiff":    "Off",
    "PkgDiff":        "Off",
    "ABIView":        "Off",
    "ABIDiff":        "Off"
  },
  {
    "Number":         "1.0.4",
    "Installed":      "installed/libsodium/1.0.4",
    "Source":         "src/libsodium/1.0.4/libsodium-1.0.4.tar.gz",
    "Changelog":      "ChangeLog",
    "HeadersDiff":    "Off",
    "PkgDiff":        "Off",
    "ABIView":        "Off",
    "ABIDiff":        "Off"
  },
  {
    "Number":         "1.0.3",
    "Installed":      "installed/libsodium/1.0.3",
    "Source":         "src/libsodium/1.0.3/libsodium-1.0.3.tar.gz",
    "Changelog":      "ChangeLog",
    "HeadersDiff":    "Off",
    "PkgDiff":        "Off",
    "ABIView":        "Off",
    "ABIDiff":        "Off"
  },
  {
    "Number":         "1.0.1",
    "Installed":      "installed/libsodium/1.0.1",
    "Source":         "src/libsodium/1.0.1/libsodium-1.0.1.tar.gz",
    "Changelog":      "ChangeLog",
    "HeadersDiff":    "Off",
    "PkgDiff":        "Off",
    "ABIView":        "Off",
    "ABIDiff":        "Off"
  },
  {
    "Number":         "1.0.0",
    "Installed":      "installed/libsodium/1.0.0",
    "Source":         "src/libsodium/1.0.0/libsodium-1.0.0.tar.gz",
    "Changelog":      "ChangeLog",
    "HeadersDiff":    "Off",
    "PkgDiff":        "Off",
    "ABIView":        "Off",
    "ABIDiff":        "Off"
  },
  {
    "Number":         "0.7.1",
    "Installed":      "installed/libsodium/0.7.1",
    "Source":         "src/libsodium/0.7.1/libsodium-0.7.1.tar.gz",
    "Changelog":      "ChangeLog",
    "HeadersDiff":    "Off",
    "PkgDiff":        "Off",
    "ABIView":        "Off",
    "ABIDiff":        "Off"
  },
  {
    "Number":         "0.7.0",
    "Installed":      "installed/libsodium/0.7.0",
    "Source":         "src/libsodium/0.7.0/libsodium-0.7.0.tar.gz",
    "Changelog":      "ChangeLog",
    "HeadersDiff":    "Off",
    "PkgDiff":        "Off",
    "ABIView":        "Off",
    "ABIDiff":        "Off"
  },
  {
    "Number":         "0.6.1",
    "Installed":      "installed/libsodium/0.6.1",
    "Source":         "src/libsodium/0.6.1/libsodium-0.6.1.tar.gz",
    "Changelog":      "ChangeLog",
    "HeadersDiff":    "Off",
    "PkgDiff":        "Off",
    "ABIView":        "Off",
    "ABIDiff":        "Off"
  },
  {
    "Number":         "0.6.0",
    "Installed":      "installed/libsodium/0.6.0",
    "Source":         "src/libsodium/0.6.0/libsodium-0.6.0.tar.gz",
    "Changelog":      "ChangeLog",
    "HeadersDiff":    "Off",
    "PkgDiff":        "Off",
    "ABIView":        "Off",
    "ABIDiff":        "Off"
  },
  {
    "Number":         "0.5.0",
    "Installed":      "installed/libsodium/0.5.0",
    "Source":         "src/libsodium/0.5.0/libsodium-0.5.0.tar.gz",
    "Changelog":      "ChangeLog",
    "HeadersDiff":    "Off",
    "PkgDiff":        "Off",
    "ABIView":        "Off",
    "ABIDiff":        "Off"
  },
  {
    "Number":         "0.4.5",
    "Installed":      "installed/libsodium/0.4.5",
    "Source":         "src/libsodium/0.4.5/libsodium-0.4.5.tar.gz",
    "Changelog":      "ChangeLog",
    "HeadersDiff":    "Off",
    "PkgDiff":        "Off",
    "ABIView":        "Off",
    "ABIDiff":        "Off"
  },
  {
    "Number":         "0.4.4",
    "Installed":      "installed/libsodium/0.4.4",
    "Source":         "src/libsodium/0.4.4/libsodium-0.4.4.tar.gz",
    "Changelog":      "ChangeLog",
    "HeadersDiff":    "Off",
    "PkgDiff":        "Off",
    "ABIView":        "Off",
    "ABIDiff":        "Off"
  },
  {
    "Number":         "0.4.3",
    "Installed":      "installed/libsodium/0.4.3",
    "Source":         "src/libsodium/0.4.3/libsodium-0.4.3.tar.gz",
    "Changelog":      "ChangeLog",
    "HeadersDiff":    "Off",
    "PkgDiff":        "Off",
    "ABIView":        "Off",
    "ABIDiff":        "Off"
  },
  {
    "Number":         "0.4.2",
    "Installed":      "installed/libsodium/0.4.2",
    "Source":         "src/libsodium/0.4.2/libsodium-0.4.2.tar.gz",
    "Changelog":      "ChangeLog",
    "HeadersDiff":    "Off",
    "PkgDiff":        "Off",
    "ABIView":        "Off",
    "ABIDiff":        "Off"
  },
  {
    "Number":         "0.4.1",
    "Installed":      "installed/libsodium/0.4.1",
    "Source":         "src/libsodium/0.4.1/libsodium-0.4.1.tar.gz",
    "Changelog":      "ChangeLog",
    "HeadersDiff":    "Off",
    "PkgDiff":        "Off",
    "ABIView":        "Off",
    "ABIDiff":        "Off"
  },
  {
    "Number":         "0.4",
    "Installed":      "installed/libsodium/0.4",
    "Source":         "src/libsodium/0.4/libsodium-0.4.tar.gz",
    "Changelog":      "ChangeLog",
    "HeadersDiff":    "Off",
    "PkgDiff":        "Off",
    "ABIView":        "Off",
    "ABIDiff":        "Off"
  },
  {
    "Number":         "0.3",
    "Installed":      "installed/libsodium/0.3",
    "Source":         "src/libsodium/0.3/libsodium-0.3.tar.gz",
    "Changelog":      "ChangeLog",
    "HeadersDiff":    "Off",
    "PkgDiff":        "Off",
    "ABIView":        "Off",
    "ABIDiff":        "Off"
  },
  {
    "Number":         "0.2",
    "Installed":      "installed/libsodium/0.2",
    "Source":         "src/libsodium/0.2/libsodium-0.2.tar.gz",
    "Changelog":      "ChangeLog",
    "HeadersDiff":    "Off",
    "PkgDiff":        "Off",
    "ABIView":        "Off",
    "ABIDiff":        "Off"
  },
  {
    "Number":         "0.1",
    "Installed":      "installed/libsodium/0.1",
    "Source":         "src/libsodium/0.1/libsodium-0.1.tar.gz",
    "Changelog":      "ChangeLog",
    "HeadersDiff":    "Off",
    "PkgDiff":        "Off",
    "ABIView":        "Off",
    "ABIDiff":        "Off"
  }]
}
