{
  "Name":           "lxc",
  "Title":          "LXC",
  "SourceUrl":      "https://github.com/lxc/lxc/tags",
  "Maintainer":     "Andrey P.",
  "MaintainerUrl":  "http://abi-laboratory.pro/",
  "Configure":      "--disable-bash --disable-python --disable-doc --disable-lua --disable-tests --disable-examples --disable-static --with-systemdsystemunitdir={INSTALL_TO}/share",
  "PostInstall":    "rm -fr {INSTALL_TO}/lxc",
  "HeadersDiff":    "Off",

  "Versions": [
  {
    "Number":         "2.0.8",
    "Installed":      "installed/lxc/2.0.8",
    "Source":         "src/lxc/2.0.8/lxc-2.0.8.tar.gz",
    "Changelog":      "Off",
    "HeadersDiff":    "Off",
    "PkgDiff":        "Off",
    "ABIView":        "Off",
    "ABIDiff":        "Off"
  },
  {
    "Number":         "2.0.7",
    "Installed":      "installed/lxc/2.0.7",
    "Source":         "src/lxc/2.0.7/lxc-2.0.7.tar.gz",
    "Changelog":      "Off",
    "HeadersDiff":    "Off",
    "PkgDiff":        "Off",
    "ABIView":        "Off",
    "ABIDiff":        "Off"
  },
  {
    "Number":         "2.0.6",
    "Installed":      "installed/lxc/2.0.6",
    "Source":         "src/lxc/2.0.6/lxc-2.0.6.tar.gz",
    "Changelog":      "Off",
    "HeadersDiff":    "Off",
    "PkgDiff":        "Off",
    "ABIView":        "Off",
    "ABIDiff":        "Off"
  },
  {
    "Number":         "2.0.5",
    "Installed":      "installed/lxc/2.0.5",
    "Source":         "src/lxc/2.0.5/lxc-2.0.5.tar.gz",
    "Changelog":      "Off",
    "HeadersDiff":    "Off",
    "PkgDiff":        "Off",
    "ABIView":        "Off",
    "ABIDiff":        "Off"
  },
  {
    "Number":         "2.0.4",
    "Installed":      "installed/lxc/2.0.4",
    "Source":         "src/lxc/2.0.4/lxc-2.0.4.tar.gz",
    "Changelog":      "Off",
    "HeadersDiff":    "Off",
    "PkgDiff":        "Off",
    "ABIView":        "Off",
    "ABIDiff":        "Off"
  },
  {
    "Number":         "2.0.3",
    "Installed":      "installed/lxc/2.0.3",
    "Source":         "src/lxc/2.0.3/lxc-2.0.3.tar.gz",
    "Changelog":      "Off",
    "HeadersDiff":    "Off",
    "PkgDiff":        "Off",
    "ABIView":        "Off",
    "ABIDiff":        "Off"
  },
  {
    "Number":         "2.0.2",
    "Installed":      "installed/lxc/2.0.2",
    "Source":         "src/lxc/2.0.2/lxc-2.0.2.tar.gz",
    "Changelog":      "Off",
    "HeadersDiff":    "Off",
    "PkgDiff":        "Off",
    "ABIView":        "Off",
    "ABIDiff":        "Off"
  },
  {
    "Number":         "2.0.1",
    "Installed":      "installed/lxc/2.0.1",
    "Source":         "src/lxc/2.0.1/lxc-2.0.1.tar.gz",
    "Changelog":      "Off",
    "HeadersDiff":    "Off",
    "PkgDiff":        "Off",
    "ABIView":        "Off",
    "ABIDiff":        "Off"
  },
  {
    "Number":         "2.0.0",
    "Installed":      "installed/lxc/2.0.0",
    "Source":         "src/lxc/2.0.0/lxc-2.0.0.tar.gz",
    "Changelog":      "Off",
    "HeadersDiff":    "Off",
    "PkgDiff":        "Off",
    "ABIView":        "Off",
    "ABIDiff":        "Off"
  },
  {
    "Number":         "1.1.5",
    "Installed":      "installed/lxc/1.1.5",
    "Source":         "src/lxc/1.1.5/lxc-1.1.5.tar.gz",
    "Changelog":      "Off",
    "HeadersDiff":    "Off",
    "PkgDiff":        "Off",
    "ABIView":        "Off",
    "ABIDiff":        "Off"
  },
  {
    "Number":         "1.1.4",
    "Installed":      "installed/lxc/1.1.4",
    "Source":         "src/lxc/1.1.4/lxc-1.1.4.tar.gz",
    "Changelog":      "Off",
    "HeadersDiff":    "Off",
    "PkgDiff":        "Off",
    "ABIView":        "Off",
    "ABIDiff":        "Off"
  },
  {
    "Number":         "1.1.3",
    "Installed":      "installed/lxc/1.1.3",
    "Source":         "src/lxc/1.1.3/lxc-1.1.3.tar.gz",
    "Changelog":      "Off",
    "HeadersDiff":    "Off",
    "PkgDiff":        "Off",
    "ABIView":        "Off",
    "ABIDiff":        "Off"
  },
  {
    "Number":         "1.1.2",
    "Installed":      "installed/lxc/1.1.2",
    "Source":         "src/lxc/1.1.2/lxc-1.1.2.tar.gz",
    "Changelog":      "Off",
    "HeadersDiff":    "Off",
    "PkgDiff":        "Off",
    "ABIView":        "Off",
    "ABIDiff":        "Off"
  },
  {
    "Number":         "1.1.1",
    "Installed":      "installed/lxc/1.1.1",
    "Source":         "src/lxc/1.1.1/lxc-1.1.1.tar.gz",
    "Changelog":      "Off",
    "HeadersDiff":    "Off",
    "PkgDiff":        "Off",
    "ABIView":        "Off",
    "ABIDiff":        "Off"
  },
  {
    "Number":         "1.1.0",
    "Installed":      "installed/lxc/1.1.0",
    "Source":         "src/lxc/1.1.0/lxc-1.1.0.tar.gz",
    "Changelog":      "Off",
    "HeadersDiff":    "Off",
    "PkgDiff":        "Off",
    "ABIView":        "Off",
    "ABIDiff":        "Off"
  },
  {
    "Number":         "1.0.10",
    "Installed":      "installed/lxc/1.0.10",
    "Source":         "src/lxc/1.0.10/lxc-1.0.10.tar.gz",
    "Changelog":      "Off",
    "HeadersDiff":    "Off",
    "PkgDiff":        "Off",
    "ABIView":        "Off",
    "ABIDiff":        "Off"
  },
  {
    "Number":         "1.0.9",
    "Installed":      "installed/lxc/1.0.9",
    "Source":         "src/lxc/1.0.9/lxc-1.0.9.tar.gz",
    "Changelog":      "Off",
    "HeadersDiff":    "Off",
    "PkgDiff":        "Off",
    "ABIView":        "Off",
    "ABIDiff":        "Off"
  },
  {
    "Number":         "1.0.8",
    "Installed":      "installed/lxc/1.0.8",
    "Source":         "src/lxc/1.0.8/lxc-1.0.8.tar.gz",
    "Changelog":      "Off",
    "HeadersDiff":    "Off",
    "PkgDiff":        "Off",
    "ABIView":        "Off",
    "ABIDiff":        "Off"
  },
  {
    "Number":         "1.0.7",
    "Installed":      "installed/lxc/1.0.7",
    "Source":         "src/lxc/1.0.7/lxc-1.0.7.tar.gz",
    "Changelog":      "Off",
    "HeadersDiff":    "Off",
    "PkgDiff":        "Off",
    "ABIView":        "Off",
    "ABIDiff":        "Off"
  },
  {
    "Number":         "1.0.6",
    "Installed":      "installed/lxc/1.0.6",
    "Source":         "src/lxc/1.0.6/lxc-1.0.6.tar.gz",
    "Changelog":      "Off",
    "HeadersDiff":    "Off",
    "PkgDiff":        "Off",
    "ABIView":        "Off",
    "ABIDiff":        "Off"
  },
  {
    "Number":         "1.0.5",
    "Installed":      "installed/lxc/1.0.5",
    "Source":         "src/lxc/1.0.5/lxc-1.0.5.tar.gz",
    "Changelog":      "Off",
    "HeadersDiff":    "Off",
    "PkgDiff":        "Off",
    "ABIView":        "Off",
    "ABIDiff":        "Off"
  },
  {
    "Number":         "1.0.4",
    "Installed":      "installed/lxc/1.0.4",
    "Source":         "src/lxc/1.0.4/lxc-1.0.4.tar.gz",
    "Changelog":      "Off",
    "HeadersDiff":    "Off",
    "PkgDiff":        "Off",
    "ABIView":        "Off",
    "ABIDiff":        "Off"
  },
  {
    "Number":         "1.0.3",
    "Installed":      "installed/lxc/1.0.3",
    "Source":         "src/lxc/1.0.3/lxc-1.0.3.tar.gz",
    "Changelog":      "Off",
    "HeadersDiff":    "Off",
    "PkgDiff":        "Off",
    "ABIView":        "Off",
    "ABIDiff":        "Off"
  },
  {
    "Number":         "1.0.2",
    "Installed":      "installed/lxc/1.0.2",
    "Source":         "src/lxc/1.0.2/lxc-1.0.2.tar.gz",
    "Changelog":      "Off",
    "HeadersDiff":    "Off",
    "PkgDiff":        "Off",
    "ABIView":        "Off",
    "ABIDiff":        "Off"
  },
  {
    "Number":         "1.0.1",
    "Installed":      "installed/lxc/1.0.1",
    "Source":         "src/lxc/1.0.1/lxc-1.0.1.tar.gz",
    "Changelog":      "Off",
    "HeadersDiff":    "Off",
    "PkgDiff":        "Off",
    "ABIView":        "Off",
    "ABIDiff":        "Off"
  }]
}
