{
  "Name":           "protobuf",
  "SourceUrl":      "https://github.com/google/protobuf/tags",
  "Git":            "https://github.com/google/protobuf.git",
  "Maintainer":     "Andrey P.",
  "MaintainerUrl":  "http://abi-laboratory.pro/",
  "HeadersDiff":    "Off",

  "Versions": [
  {
    "Number":         "current",
    "Installed":      "installed/protobuf/current",
    "Source":         "src/protobuf/current",
    "Changelog":      "On",
    "HeadersDiff":    "Off",
    "PkgDiff":        "Off",
    "ABIView":        "Off",
    "ABIDiff":        "Off"
  },
  {
    "Number":         "3.1.0",
    "Installed":      "installed/protobuf/3.1.0",
    "Source":         "src/protobuf/3.1.0/protobuf-3.1.0.tar.gz",
    "Changelog":      "CHANGES.txt",
    "HeadersDiff":    "Off",
    "PkgDiff":        "Off",
    "ABIView":        "Off",
    "ABIDiff":        "Off"
  },
  {
    "Number":         "3.0.2",
    "Installed":      "installed/protobuf/3.0.2",
    "Source":         "src/protobuf/3.0.2/protobuf-3.0.2.tar.gz",
    "Changelog":      "CHANGES.txt",
    "HeadersDiff":    "Off",
    "PkgDiff":        "Off",
    "ABIView":        "Off",
    "ABIDiff":        "Off"
  },
  {
    "Number":         "3.0.0",
    "Installed":      "installed/protobuf/3.0.0",
    "Source":         "src/protobuf/3.0.0/protobuf-3.0.0.tar.gz",
    "Changelog":      "CHANGES.txt",
    "HeadersDiff":    "Off",
    "PkgDiff":        "Off",
    "ABIView":        "Off",
    "ABIDiff":        "Off"
  },
  {
    "Number":         "2.6.1",
    "Installed":      "installed/protobuf/2.6.1",
    "Source":         "src/protobuf/2.6.1/protobuf-2.6.1.tar.gz",
    "Changelog":      "CHANGES.txt",
    "HeadersDiff":    "Off",
    "PkgDiff":        "Off",
    "ABIView":        "Off",
    "ABIDiff":        "Off"
  },
  {
    "Number":         "2.6.0",
    "Installed":      "installed/protobuf/2.6.0",
    "Source":         "src/protobuf/2.6.0/protobuf-2.6.0.tar.gz",
    "Changelog":      "CHANGES.txt",
    "HeadersDiff":    "Off",
    "PkgDiff":        "Off",
    "ABIView":        "Off",
    "ABIDiff":        "Off"
  },
  {
    "Number":         "2.5.0",
    "Installed":      "installed/protobuf/2.5.0",
    "Source":         "src/protobuf/2.5.0/protobuf-2.5.0.tar.gz",
    "Changelog":      "CHANGES.txt",
    "HeadersDiff":    "Off",
    "PkgDiff":        "Off",
    "ABIView":        "Off",
    "ABIDiff":        "Off"
  },
  {
    "Number":         "2.4.1",
    "Installed":      "installed/protobuf/2.4.1",
    "Source":         "src/protobuf/2.4.1/protobuf-2.4.1.tar.gz",
    "Changelog":      "CHANGES.txt",
    "HeadersDiff":    "Off",
    "PkgDiff":        "Off",
    "ABIView":        "Off",
    "ABIDiff":        "Off"
  },
  {
    "Number":         "2.3.0",
    "Installed":      "installed/protobuf/2.3.0",
    "Source":         "src/protobuf/2.3.0/protobuf-2.3.0.tar.bz2",
    "Changelog":      "CHANGES.txt",
    "HeadersDiff":    "Off",
    "PkgDiff":        "Off",
    "ABIView":        "Off",
    "ABIDiff":        "Off"
  },
  {
    "Number":         "2.2.0",
    "Installed":      "installed/protobuf/2.2.0",
    "Source":         "src/protobuf/2.2.0/protobuf-2.2.0.tar.bz2",
    "Changelog":      "CHANGES.txt",
    "HeadersDiff":    "Off",
    "PkgDiff":        "Off",
    "ABIView":        "Off",
    "ABIDiff":        "Off"
  }]
}
